{
  "request": {
    "method": "GET",
    "url": "https://worksheets-web-api-test.azurewebsites.net/api/sql/SQL-Shared/db-object/test1/testView1/Fields,PrimaryKeys,sqltext",
    "headers": [
      {
        "name": "Content-Type",
        "value": "application/json",
        "active": true
      },
      {
        "name": "Authorization",
        "value": "Bearer {{authentication_token}}",
        "active": true
      }
    ],
    "queryParameters": [],
    "contentType": "application/json",
    "auth": {
      "type": "None"
    }
  },
  "workflows": {
    "failOnError": true,
    "include": [
      "@common"
    ],
    "vars": {},
    "workflowsMap": {
      "pre-request-actions": [],
      "success-response-actions": [],
      "error-response-actions": []
    },
    "consts": {}
  },
  "scripts": "def preRequest():\n  print(session)\n  print(app)\n  print(app.user)\n  app.testVal = \"TestValue\"\n  res = httpGet(\"https://restcountries.eu/rest/v2/region/oceania\")\n  print(res)\n  quandl = httpGet(\"https://www.quandl.com/api/v3/datasets/CHRIS/MGEX_MW5.json?api_key=LEM5mQqZUZt2eWjiPJtF\")\n  print(quandl.dataset.data)\n  chartConfig = {\"chartType\": \"Bar\", \"bindingX\": \"name\", \"header\": \"Country population\",\n    \"series\": [{name: \"name\", binding: \"population\"}]\n  }\n  plotChart(res, \"Oceania Population\", chartConfig)\n  runRequest(\"Test1.Authentication\", False, False)\n  session.sTest = \"sTestVal1\"\n\ndef successResponse(response):\n  print(\"successResponse\")\n  print(app.testVal)\n  print(session.sTest)\n  print(response)\n  error(\"Test error message - 0\")\n  showInObjectExplorer(response.body, \"Content\")\n  showInJSON(response.headers, \"Header\")\n  assert(True, \"TestView\", \"Test Success Description\")\n  assert(True, \"TestView\", \"Test Failed Description\")\n  error(\"Test error message - 1\")\n  error(\"Test error message - 2\")\n  error(\"Test error message - 3\")\n\ndef errorResponse(error):\n  print(error)",
  "uiSettings": {
    "isRequestPanelCollapsed": false,
    "showObjectExplorer": true,
    "showContent": true,
    "showHeader": true,
    "showWorkflow": true,
    "showPages": true
  },
  "dynamicPages": [],
  "isPublic": true,
  "id": 76,
  "linkType": "RestRequest",
  "folder": "Tests",
  "ownerName": "Test1",
  "name": "ViewRequest",
  "description": "View test request"
}
